neuroevo/__init__.py
neuroevo/models.py
neuroevo-0.0.8.dist-info/LICENSE
neuroevo-0.0.8.dist-info/METADATA
neuroevo-0.0.8.dist-info/WHEEL
neuroevo-0.0.8.dist-info/top_level.txt
neuroevo-0.0.8.dist-info/RECORD
