Metadata-Version: 2.1
Name: neuroevo
Version: 0.0.8
Summary: Training neural networks with evolutionary and particle swarm algorithms
Author-email: Philip Schroeder <pschroe9@jhu.edu>
License: Copyright (c) 2018 The Python Packaging Authority
Project-URL: Homepage, https://github.com/NeuroEvo/neuroevo
Classifier: Programming Language :: Python :: 3
Classifier: License :: OSI Approved :: MIT License
Classifier: Operating System :: OS Independent
Requires-Python: >=3.0
License-File: LICENSE
